devchat/__init__.py
devchat/__main__.py
devchat/_cli/__init__.py
devchat/_cli/errors.py
devchat/_cli/log.py
devchat/_cli/main.py
devchat/_cli/prompt.py
devchat/_cli/route.py
devchat/_cli/router.py
devchat/_cli/run.py
devchat/_cli/topic.py
devchat/_cli/utils.py
devchat/_service/README.md
devchat/_service/__init__.py
devchat/_service/config.py
devchat/_service/gunicorn_logging.py
devchat/_service/main.py
devchat/_service/route/__init__.py
devchat/_service/route/logs.py
devchat/_service/route/message.py
devchat/_service/route/topics.py
devchat/_service/route/workflows.py
devchat/_service/schema/__init__.py
devchat/_service/schema/request.py
devchat/_service/schema/response.py
devchat/_service/uvicorn_logging.py
devchat/anthropic/__init__.py
devchat/anthropic/anthropic_chat.py
devchat/assistant.py
devchat/chat.py
devchat/chatmark/.gitignore
devchat/chatmark/README.md
devchat/chatmark/__init__.py
devchat/chatmark/chatmark_example/README.md
devchat/chatmark/chatmark_example/main.py
devchat/chatmark/form.py
devchat/chatmark/iobase.py
devchat/chatmark/step.py
devchat/chatmark/widgets.py
devchat/config.py
devchat/engine/__init__.py
devchat/engine/command_parser.py
devchat/engine/command_runner.py
devchat/engine/namespace.py
devchat/engine/recursive_prompter.py
devchat/engine/router.py
devchat/engine/util.py
devchat/ide/__init__.py
devchat/ide/idea_services.py
devchat/ide/rpc.py
devchat/ide/service.py
devchat/ide/types.py
devchat/ide/vscode_services.py
devchat/llm/__init__.py
devchat/llm/chat.py
devchat/llm/openai.py
devchat/llm/pipeline.py
devchat/llm/text_confirm.py
devchat/llm/tools_call.py
devchat/memory/__init__.py
devchat/memory/base.py
devchat/memory/fixsize_memory.py
devchat/message.py
devchat/msg/__init__.py
devchat/msg/chatting.py
devchat/msg/log_util.py
devchat/msg/schema.py
devchat/msg/topic_util.py
devchat/msg/user_info.py
devchat/msg/util.py
devchat/openai/__init__.py
devchat/openai/http_openai.py
devchat/openai/openai_chat.py
devchat/openai/openai_message.py
devchat-0.3.0.dist-info/LICENSE
devchat-0.3.0.dist-info/METADATA
devchat-0.3.0.dist-info/WHEEL
devchat-0.3.0.dist-info/entry_points.txt
devchat-0.3.0.dist-info/RECORD
