Metadata-Version: 2.1
Name: devchat
Version: 0.3.0
Summary: DevChat is an open-source tool that helps developers write prompts to generate code and documentation.
Home-page: https://github.com/devchat-ai/devchat
License: Apache-2.0
Author: DevChat Team
Author-email: hello@devchat.ai
Requires-Python: >=3.8,<4.0
Classifier: Development Status :: 4 - Beta
Classifier: Intended Audience :: Developers
Classifier: Intended Audience :: Education
Classifier: Intended Audience :: Information Technology
Classifier: License :: OSI Approved :: Apache Software License
Classifier: Programming Language :: Python :: 3
Classifier: Programming Language :: Python :: 3.8
Classifier: Programming Language :: Python :: 3.9
Classifier: Programming Language :: Python :: 3.10
Classifier: Programming Language :: Python :: 3.11
Classifier: Topic :: Scientific/Engineering :: Artificial Intelligence
Classifier: Topic :: Software Development
Requires-Dist: colorama (>=0.4.6,<0.5.0)
Requires-Dist: fastapi (>=0.111.0,<0.112.0)
Requires-Dist: gitpython (>=3.1.32,<4.0.0)
Requires-Dist: gunicorn (>=22.0.0,<23.0.0)
Requires-Dist: importlib-metadata (>=6.8.0,<7.0.0)
Requires-Dist: importlib-resources (>=6.1.1,<7.0.0)
Requires-Dist: loguru (>=0.7.2,<0.8.0)
Requires-Dist: networkx (>=3.1,<4.0)
Requires-Dist: openai (>=1.0rc,<2.0)
Requires-Dist: oyaml (>=1.0,<2.0)
Requires-Dist: pathspec (>=0.12.1,<0.13.0)
Requires-Dist: pydantic (==1.10.14)
Requires-Dist: rich_click (>=1.6.1,<2.0.0)
Requires-Dist: tenacity (>=8.2.3,<9.0.0)
Requires-Dist: tiktoken (>0.4.0)
Requires-Dist: tinydb (>=4.7.1,<5.0.0)
Requires-Dist: urllib3 (<2.0)
Requires-Dist: uvicorn[standard] (>=0.30.1,<0.31.0)
Requires-Dist: win32-setctime (>=1.1.0,<2.0.0)
